hg_credentials-0.1.2-py3.12-nspkg.pth
hgext3rd/credentials/__init__.py
hgext3rd/credentials/helper.py
hgext3rd/credentials/keychain.abi3.so
hgext3rd/credentials/keychain.py
hgext3rd/credentials/secretstorage.py
hg_credentials-0.1.2.dist-info/COPYING
hg_credentials-0.1.2.dist-info/METADATA
hg_credentials-0.1.2.dist-info/WHEEL
hg_credentials-0.1.2.dist-info/namespace_packages.txt
hg_credentials-0.1.2.dist-info/top_level.txt
hg_credentials-0.1.2.dist-info/RECORD
