Metadata-Version: 2.1
Name: hg-credentials
Version: 0.1.2
Summary: Mercurial extension for storing passwords securely
Home-page: http://foss.heptapod.net/mercurial/hg-credentials
Author: Dan Villiom Podlaski Christiansen
Author-email: danchr@gmail.com
License: GPL-2.0-or-later
Classifier: Development Status :: 2 - Pre-Alpha
Classifier: Intended Audience :: Developers
Classifier: Intended Audience :: System Administrators
Classifier: License :: OSI Approved :: GNU General Public License (GPL)
Classifier: Programming Language :: Python
Classifier: Topic :: Software Development :: Version Control
Classifier: Environment :: MacOS X
Requires-Python: >=3.6
License-File: COPYING
Requires-Dist: secretstorage ; sys_platform != "darwin" and os_name == "posix"
